MANIFEST.in
README.md
setup.py
mdio/__init__.py
mdio/_version.py
mdio/base.py
mdio/dcdio.py
mdio/fastrmsd.c
mdio/fastrmsd.pyx
mdio/groio.py
mdio/mdcrdio.py
mdio/mdioio.py
mdio/mdtio.py
mdio/ncio.py
mdio/openmmio.py
mdio/pdbio.py
mdio/rmsd_utils.py
mdio/rmsd_utils_correct.py
mdio/rstio.py
mdio/utilities.py
mdio/xtcio.py
mdio/xtcutils.c
mdio/xtcutils.pyx
mdio.egg-info/PKG-INFO
mdio.egg-info/PKG-INFO-Charles’s iMac
mdio.egg-info/SOURCES-Charles’s iMac.txt
mdio.egg-info/SOURCES.txt
mdio.egg-info/dependency_links.txt
mdio.egg-info/requires.txt
mdio.egg-info/top_level.txt
mdio/src/fastrmsd.c
mdio/src/xtcutils.c
test/test_base.py
test/test_dcdio.py
test/test_groio.py
test/test_io.py
test/test_mdcrdio.py
test/test_mdioio.py
test/test_mdtio.py
test/test_mpi.py
test/test_ncio.py
test/test_openmmio.py
test/test_pdbio.py
test/test_rstio.py
test/test_xtcio.py
test/testdcdio2.py
test/testncio2.py
test/testxtcio2.py