Metadata-Version: 2.1
Name: mdio
Version: 0.2.1
Summary: Basic I/O for MD trajectory files
Home-page: https://bitbucket.org/claughton/mdio
Author: Charlie Laughton
Author-email: charles.laughton@nottingham.ac.uk
License: UNKNOWN
Platform: UNKNOWN
Classifier: Programming Language :: Python :: 3
Classifier: License :: OSI Approved :: BSD License
Classifier: Development Status :: 3 - Alpha
